tfx/__init__.py
tfx/dependencies.py
tfx/version.py
tfx/benchmarks/__init__.py
tfx/benchmarks/benchmark_base.py
tfx/benchmarks/benchmark_dataset.py
tfx/benchmarks/benchmark_utils.py
tfx/benchmarks/regenerate_datasets.py
tfx/benchmarks/tfma_benchmark_base.py
tfx/benchmarks/tfma_benchmark_chicago_taxi.py
tfx/benchmarks/tfma_v2_benchmark_base.py
tfx/benchmarks/tfma_v2_benchmark_chicago_taxi.py
tfx/benchmarks/tft_benchmark_base.py
tfx/benchmarks/tft_benchmark_chicago_taxi.py
tfx/benchmarks/datasets/__init__.py
tfx/benchmarks/datasets/chicago_taxi/__init__.py
tfx/benchmarks/datasets/chicago_taxi/dataset.py
tfx/components/__init__.py
tfx/components/base/__init__.py
tfx/components/base/base_component.py
tfx/components/base/base_driver.py
tfx/components/base/base_executor.py
tfx/components/base/base_node.py
tfx/components/base/executor_spec.py
tfx/components/bulk_inferrer/__init__.py
tfx/components/bulk_inferrer/component.py
tfx/components/bulk_inferrer/component_test.py
tfx/components/bulk_inferrer/executor.py
tfx/components/bulk_inferrer/executor_test.py
tfx/components/bulk_inferrer/prediction_to_example_utils.py
tfx/components/bulk_inferrer/prediction_to_example_utils_test.py
tfx/components/common_nodes/__init__.py
tfx/components/common_nodes/importer_node.py
tfx/components/common_nodes/resolver_node.py
tfx/components/evaluator/__init__.py
tfx/components/evaluator/component.py
tfx/components/evaluator/component_test.py
tfx/components/evaluator/constants.py
tfx/components/evaluator/executor.py
tfx/components/evaluator/executor_test.py
tfx/components/example_gen/__init__.py
tfx/components/example_gen/base_example_gen_executor.py
tfx/components/example_gen/base_example_gen_executor_test.py
tfx/components/example_gen/component.py
tfx/components/example_gen/component_test.py
tfx/components/example_gen/driver.py
tfx/components/example_gen/driver_test.py
tfx/components/example_gen/utils.py
tfx/components/example_gen/utils_test.py
rflow_ml_pipelines_sdk-1.1.18.dist-info/LICENSE
rflow_ml_pipelines_sdk-1.1.18.dist-info/METADATA
rflow_ml_pipelines_sdk-1.1.18.dist-info/WHEEL
rflow_ml_pipelines_sdk-1.1.18.dist-info/namespace_packages.txt
rflow_ml_pipelines_sdk-1.1.18.dist-info/top_level.txt
rflow_ml_pipelines_sdk-1.1.18.dist-info/RECORD
